autotm/__init__.py
autotm/abstract_params.py
autotm/algorithms_for_tuning/__init__.py
autotm/algorithms_for_tuning/bayesian_optimization/__init__.py
autotm/algorithms_for_tuning/bayesian_optimization/bayes_opt.py
autotm/algorithms_for_tuning/genetic_algorithm/__init__.py
autotm/algorithms_for_tuning/genetic_algorithm/config.yaml
autotm/algorithms_for_tuning/genetic_algorithm/crossover.py
autotm/algorithms_for_tuning/genetic_algorithm/ga.py
autotm/algorithms_for_tuning/genetic_algorithm/genetic_algorithm.py
autotm/algorithms_for_tuning/genetic_algorithm/mutation.py
autotm/algorithms_for_tuning/genetic_algorithm/selection.py
autotm/algorithms_for_tuning/genetic_algorithm/statistics_collector.py
autotm/algorithms_for_tuning/genetic_algorithm/strategy.py
autotm/algorithms_for_tuning/genetic_algorithm/surrogate.py
autotm/algorithms_for_tuning/individuals.py
autotm/algorithms_for_tuning/nelder_mead_optimization/__init__.py
autotm/algorithms_for_tuning/nelder_mead_optimization/nelder_mead.py
autotm/base.py
autotm/batch_vect_utils.py
autotm/clustering.py
autotm/content_splitter.py
autotm/data_generator/synthetic_data_generation.ipynb
autotm/fitness/__init__.py
autotm/fitness/base_score.py
autotm/fitness/cluster_tasks.py
autotm/fitness/estimator.py
autotm/fitness/external_scores.py
autotm/fitness/local_tasks.py
autotm/fitness/tm.py
autotm/graph_ga.py
autotm/infer.py
autotm/main.py
autotm/main_fitness_worker.py
autotm/make-recovery-file.py
autotm/params.py
autotm/params_logging_utils.py
autotm/pipeline.py
autotm/preprocessing/__init__.py
autotm/preprocessing/cooc.py
autotm/preprocessing/dictionaries_preparation.py
autotm/preprocessing/text_preprocessing.py
autotm/schemas.py
autotm/utils.py
autotm/visualization/__init__.py
autotm/visualization/dynamic_tracker.py
autotm-0.2.3.4.dist-info/LICENSE
autotm-0.2.3.4.dist-info/METADATA
autotm-0.2.3.4.dist-info/WHEEL
autotm-0.2.3.4.dist-info/entry_points.txt
autotm-0.2.3.4.dist-info/RECORD
