Metadata-Version: 2.1
Name: autotm
Version: 0.2.3.4
Summary: Automatic hyperparameters tuning for topic models (ARTM approach) using evolutionary algorithms
Home-page: https://autotm.readthedocs.io/en/latest/
License: Apache-2.0
Author: Khodorchenko Maria
Author-email: mariyaxod@yandex.ru
Requires-Python: >=3.9,<3.12
Classifier: License :: OSI Approved :: Apache Software License
Classifier: Programming Language :: Python :: 3
Classifier: Programming Language :: Python :: 3.9
Classifier: Programming Language :: Python :: 3.10
Classifier: Programming Language :: Python :: 3.11
Requires-Dist: PyMySQL
Requires-Dist: PyYAML (==5.3.1)
Requires-Dist: bigartm (==0.9.2)
Requires-Dist: billiard
Requires-Dist: celery (>=4.4.7)
Requires-Dist: click (==8.0.1)
Requires-Dist: dataclasses-json
Requires-Dist: dill
Requires-Dist: gensim (>=4.1.2,<5.0.0)
Requires-Dist: hyperopt
Requires-Dist: jinja2 (==3.0)
Requires-Dist: mlflow
Requires-Dist: nltk
Requires-Dist: numpy
Requires-Dist: openai (>=1.31.0,<2.0.0)
Requires-Dist: pandas
Requires-Dist: plotly
Requires-Dist: protobuf (<=3.20.0)
Requires-Dist: psycopg2-binary
Requires-Dist: pydantic (==2.6.0)
Requires-Dist: pymongo (==3.11.3)
Requires-Dist: pymystem3
Requires-Dist: pytest
Requires-Dist: redis (==3.5.3)
Requires-Dist: scikit-learn (>=1.1.1,<2.0.0)
Requires-Dist: scipy (<=1.10.1)
Requires-Dist: seaborn (>=0.13.2,<0.14.0)
Requires-Dist: spacy (>=3.5)
Requires-Dist: spacy-langdetect
Requires-Dist: tqdm (==4.50.2)
Project-URL: Repository, https://github.com/ngc436/AutoTM
